sym/__init__.py
sym/flow/__init__.py
sym/flow/cli/__init__.py
sym/flow/cli/code_generation_templates/__init__.py
sym/flow/cli/code_generation_templates/core/README.md
sym/flow/cli/code_generation_templates/core/__init__.py
sym/flow/cli/code_generation_templates/core/connectors/__init__.py
sym/flow/cli/code_generation_templates/core/connectors/connectors.tf
sym/flow/cli/code_generation_templates/core/connectors/iam_connector.tf
sym/flow/cli/code_generation_templates/core/connectors/runtime_connector.tf
sym/flow/cli/code_generation_templates/core/connectors/runtime_connector_with_account_id_safelist.tf
sym/flow/cli/code_generation_templates/core/connectors/sso_connector.tf
sym/flow/cli/code_generation_templates/core/environment.tf
sym/flow/cli/code_generation_templates/core/environment_with_runtime.tf
sym/flow/cli/code_generation_templates/core/secrets.tf
sym/flow/cli/code_generation_templates/core/versions.tf
sym/flow/cli/code_generation_templates/flows/__init__.py
sym/flow/cli/code_generation_templates/flows/approval_impl.txt
sym/flow/cli/code_generation_templates/flows/approval_only.tf
sym/flow/cli/code_generation_templates/flows/aws_iam.tf
sym/flow/cli/code_generation_templates/flows/aws_lambda.tf
sym/flow/cli/code_generation_templates/flows/aws_sso.tf
sym/flow/cli/code_generation_templates/flows/aws_sso_group_target.tf
sym/flow/cli/code_generation_templates/flows/aws_sso_permission_set_target.tf
sym/flow/cli/code_generation_templates/flows/impl.txt
sym/flow/cli/code_generation_templates/flows/lambda_handler.txt
sym/flow/cli/code_generation_templates/flows/lambda_impl.txt
sym/flow/cli/code_generation_templates/flows/okta.tf
sym/flow/cli/code_generation_templates/migration/__init__.py
sym/flow/cli/code_generation_templates/migration/v8/__init__.py
sym/flow/cli/code_generation_templates/migration/v8/migration_v8.tf
sym/flow/cli/commands/__init__.py
sym/flow/cli/commands/bots/__init__.py
sym/flow/cli/commands/bots/bots.py
sym/flow/cli/commands/bots/create.py
sym_flow_cli-8.1.0.dist-info/entry_points.txt
sym_flow_cli-8.1.0.dist-info/WHEEL
sym_flow_cli-8.1.0.dist-info/METADATA
sym_flow_cli-8.1.0.dist-info/RECORD
