Metadata-Version: 2.1
Name: sym-flow-cli
Version: 8.1.0
Summary: Sym's Official CLI for Implementers
Home-page: https://symops.com/
Author: SymOps, Inc.
Author-email: pypi@symops.io
Requires-Python: >=3.8,<4.0
Classifier: Operating System :: OS Independent
Classifier: Programming Language :: Python :: 3
Classifier: Programming Language :: Python :: 3.8
Classifier: Programming Language :: Python :: 3.9
Classifier: Programming Language :: Python :: 3.10
Classifier: Programming Language :: Python :: 3.11
Classifier: Programming Language :: Python :: 3
Requires-Dist: PyYAML (>=6.0,<7.0)
Requires-Dist: auth0-python (>=3.23.1,<4.0.0)
Requires-Dist: click (>=8.0.0,<9.0.0)
Requires-Dist: cryptography (==3.4.8)
Requires-Dist: inflection (>=0.5.1,<0.6.0)
Requires-Dist: inquirer (>=2.7.0,<3.0.0)
Requires-Dist: pkce (>=1.0,<2.0)
Requires-Dist: portalocker (>=2.0.0,<3.0.0)
Requires-Dist: pydantic (>=1.8.2,<2.0.0)
Requires-Dist: python-hcl2 (>=4.3.0,<5.0.0)
Requires-Dist: requests (>=2.25,<3.0)
Requires-Dist: semver (>=2.13.0,<3.0.0)
Requires-Dist: sentry-sdk (>=1.0.0,<2.0.0)
Requires-Dist: tabulate (>=0.8.7,<0.9.0)
Project-URL: Documentation, https://docs.symops.com/docs/install-sym-flow-cli
